opengeode_geosciences/__init__.py
opengeode_geosciences/__init__.pyi
opengeode_geosciences/explicit.py
opengeode_geosciences/explicit.pyi
opengeode_geosciences/implicit.py
opengeode_geosciences/implicit.pyi
opengeode_geosciences/py.typed
opengeode_geosciences/bin/OpenGeode-Geosciences_explicit.dll
opengeode_geosciences/bin/OpenGeode-Geosciences_implicit.dll
opengeode_geosciences/bin/__init__.pyi
opengeode_geosciences/bin/opengeode_geosciences_py_explicit.cp39-win_amd64.pyd
opengeode_geosciences/bin/opengeode_geosciences_py_explicit.pyi
opengeode_geosciences/bin/opengeode_geosciences_py_implicit.cp39-win_amd64.pyd
opengeode_geosciences/bin/opengeode_geosciences_py_implicit.pyi
opengeode_geosciences-9.5.6.dist-info/METADATA
opengeode_geosciences-9.5.6.dist-info/WHEEL
opengeode_geosciences-9.5.6.dist-info/top_level.txt
opengeode_geosciences-9.5.6.dist-info/RECORD
