Metadata-Version: 2.4
Name: OpenGeode-Geosciences
Version: 9.5.6
Summary: OpenGeode module for Geosciences
Author-email: Geode-solutions <contact@geode-solutions.com>
License: MIT
Requires-Python: <3.13,>=3.9
Requires-Dist: opengeode-core==15.*,>=15.30.10
